sapientacli.py
sapientacli-0.2.1.dist-info/entry_points.txt
sapientacli-0.2.1.dist-info/LICENSE
sapientacli-0.2.1.dist-info/WHEEL
sapientacli-0.2.1.dist-info/METADATA
sapientacli-0.2.1.dist-info/RECORD
